whitebox_plugin_location/__init__.py
whitebox_plugin_location/apps.py
whitebox_plugin_location/handlers.py
whitebox_plugin_location/jsx/FlightLocationSyncServiceComponent.jsx
whitebox_plugin_location/jsx/map_layers/WhiteboxFlightPath.jsx
whitebox_plugin_location/jsx/map_layers/WhiteboxPlayerMarker.jsx
whitebox_plugin_location/jsx/stores/location_data.js
whitebox_plugin_location/migrations/0001_initial.py
whitebox_plugin_location/migrations/__init__.py
whitebox_plugin_location/models.py
whitebox_plugin_location/serializers.py
whitebox_plugin_location/services.py
whitebox_plugin_location/urls.py
whitebox_plugin_location/views.py
whitebox_plugin_location/whitebox_plugin_location.py
whitebox_test_plugin_location/__init__.py
whitebox_test_plugin_location/test_apps.py
whitebox_test_plugin_location/test_handlers.py
whitebox_test_plugin_location/test_models.py
whitebox_test_plugin_location/test_services.py
whitebox_test_plugin_location/test_whitebox_plugin_location.py
whitebox_plugin_location-0.1.1.dist-info/LICENSE
whitebox_plugin_location-0.1.1.dist-info/METADATA
whitebox_plugin_location-0.1.1.dist-info/WHEEL
whitebox_plugin_location-0.1.1.dist-info/entry_points.txt
whitebox_plugin_location-0.1.1.dist-info/RECORD
