Metadata-Version: 2.3
Name: whitebox-plugin-location
Version: 0.1.1
Summary: A plugin for Whitebox that provides location utilities and extensions
License: GNU Affero General Public License v3
Author: Milos
Author-email: hello@klined.org
Requires-Python: >=3.10.0
Classifier: License :: Other/Proprietary License
Classifier: Programming Language :: Python :: 3
Classifier: Programming Language :: Python :: 3.10
Classifier: Programming Language :: Python :: 3.11
Classifier: Programming Language :: Python :: 3.12
Classifier: Programming Language :: Python :: 3.13
